virtualenv_cache/__init__.py
virtualenv_cache/_cache.py
virtualenv_cache/_config.py
virtualenv_cache/_exceptions.py
virtualenv_cache/cli.py
virtualenv_cache/utils.py
virtualenv_cache/data/default_virtualenv_cache.toml.template
virtualenv_cache-0.0.2.dist-info/LICENSE
virtualenv_cache-0.0.2.dist-info/METADATA
virtualenv_cache-0.0.2.dist-info/WHEEL
virtualenv_cache-0.0.2.dist-info/entry_points.txt
virtualenv_cache-0.0.2.dist-info/top_level.txt
virtualenv_cache-0.0.2.dist-info/RECORD
