Metadata-Version: 2.1
Name: virtualenv-cache
Version: 0.0.2
Summary: Manage a cache of Python environments
Author-email: Fridolin Pokorny <fridolin.pokorny@gmail.com>
License: BSD-3-Clause
Project-URL: homepage, https://github.com/fridex/virtualenv-cache
Keywords: packaging,pip-tools,cache,dependencies,virtual environment,poetry,pdm,pipfile
Classifier: Development Status :: 4 - Beta
Classifier: Programming Language :: Python :: 3
Classifier: Programming Language :: Python :: 3.10
Classifier: Programming Language :: Python :: 3.11
Classifier: Programming Language :: Python :: 3.8
Classifier: Programming Language :: Python :: 3.9
Classifier: Programming Language :: Python :: 3 :: Only
Classifier: Typing :: Typed
Requires-Python: >=3.6
License-File: LICENSE
Requires-Dist: attrs
Requires-Dist: click
Requires-Dist: daiquiri
Requires-Dist: python-dateutil
Requires-Dist: rich
Requires-Dist: tomli
